rustc_dev_t_x64_win_msvc_nightly_p6/__init__.py
rustc_dev_t_x64_win_msvc_nightly_p6/data/darling_macro-4543ce35549bedf3.dll.lib
rustc_dev_t_x64_win_msvc_nightly_p6/data/displaydoc-e6bf581cd9edd608.pdb
rustc_dev_t_x64_win_msvc_nightly_p6/data/icu_provider_macros-d4f887cd84c98d98.pdb
rustc_dev_t_x64_win_msvc_nightly_p6/data/libblake3-73bdc22a13b42f4d.rmeta
rustc_dev_t_x64_win_msvc_nightly_p6/data/libcpufeatures-b10cf0371f0c3fed.rmeta
rustc_dev_t_x64_win_msvc_nightly_p6/data/libcrossbeam_utils-83c542ddf0253115.rmeta
rustc_dev_t_x64_win_msvc_nightly_p6/data/libfluent_bundle-0e793929734efcab.rmeta
rustc_dev_t_x64_win_msvc_nightly_p6/data/libgimli-5e395469dada8904.rmeta
rustc_dev_t_x64_win_msvc_nightly_p6/data/libgsgdt-bb261b0d0a51e783.rmeta
rustc_dev_t_x64_win_msvc_nightly_p6/data/liblog-4dd2cfed71f606ae.rmeta
rustc_dev_t_x64_win_msvc_nightly_p6/data/libpathdiff-67554ff29401b3e1.rmeta
rustc_dev_t_x64_win_msvc_nightly_p6/data/libpin_project_lite-eeb8aec3a268bd1f.rmeta
rustc_dev_t_x64_win_msvc_nightly_p6/data/libppv_lite86-dc65c21b1f0476dc.rmeta
rustc_dev_t_x64_win_msvc_nightly_p6/data/libpulldown_cmark_escape-eb26553775f25c3a.rmeta
rustc_dev_t_x64_win_msvc_nightly_p6/data/libregex-0c2c557ccd50c271.rmeta
rustc_dev_t_x64_win_msvc_nightly_p6/data/libregex_automata-475378b98bc68cc9.rmeta
rustc_dev_t_x64_win_msvc_nightly_p6/data/librustc_ast_ir-7a51eee9e39cfc19.rmeta
rustc_dev_t_x64_win_msvc_nightly_p6/data/librustc_driver_impl-1868cb54a6715e31.rmeta
rustc_dev_t_x64_win_msvc_nightly_p6/data/librustc_errors-38e4ee7b76dc0ea8.rmeta
rustc_dev_t_x64_win_msvc_nightly_p6/data/librustc_hir-1f08b761ec2445c2.rmeta
rustc_dev_t_x64_win_msvc_nightly_p6/data/librustc_index-6c2355c6db310b65.rmeta
rustc_dev_t_x64_win_msvc_nightly_p6/data/librustc_lexer-811be226282f8714.rmeta
rustc_dev_t_x64_win_msvc_nightly_p6/data/librustc_lint_defs-22e2cd1e8fff23b3.rmeta
rustc_dev_t_x64_win_msvc_nightly_p6/data/librustc_middle-1366453828d4b746.rmeta
rustc_dev_t_x64_win_msvc_nightly_p6-1.91.0.dist-info/METADATA
rustc_dev_t_x64_win_msvc_nightly_p6-1.91.0.dist-info/WHEEL
rustc_dev_t_x64_win_msvc_nightly_p6-1.91.0.dist-info/top_level.txt
rustc_dev_t_x64_win_msvc_nightly_p6-1.91.0.dist-info/RECORD
